xtracthub/__init__.py
xtracthub/xcs/__init__.py
xtracthub-0.3.1.dist-info/LICENSE
xtracthub-0.3.1.dist-info/METADATA
xtracthub-0.3.1.dist-info/WHEEL
xtracthub-0.3.1.dist-info/top_level.txt
xtracthub-0.3.1.dist-info/RECORD
