Metadata-Version: 2.1
Name: xtracthub
Version: 0.3.1
Summary: SDK for xtract-container-service
Home-page: https://github.com/xtracthub/xtract-container-service
Author: Ryan Wong
Author-email: rewong03@gmail.com
License: UNKNOWN
Platform: UNKNOWN
